{
  "date": "2026-07-15",
  "scan_type": "static analysis — grep for hardcoded secrets in src/ and tests/",
  "patterns_checked": [
    "secret = '...'",
    "api_key = '...'",
    "password = '...'",
    "token = '...'",
    "credential = '...'",
    "os.environ / os.getenv usage"
  ],
  "findings": {
    "hardcoded_secrets": 0,
    "all_credentials_use_env_or_keychain": true,
    "os_getenv_usage": [
      "src/nexara_prime/config.py — NEXARA_DB_PATH, NEXARA_WORKSPACE_ROOT, NEXARA_REPORT_ROOT, NEXARA_MODEL_PROVIDER, NEXARA_MOCK_MODEL, NEXARA_API_HOST, NEXARA_API_PORT",
      "src/nexara_prime/runtime.py — NEXARA_MODEL_ENDPOINT, NEXARA_MODEL_NAME",
      "src/nexara_prime/cli.py — VIRTUAL_ENV"
    ],
    "keychain_integration": "src/nexara_prime/secrets/keychain.py — macOS Keychain for provider credentials"
  },
  "verdict": "PASS — 0 hardcoded secrets"
}
